{
  "platform": "xhs",
  "url": "https://www.xiaohongshu.com/explore/6958f9db000000001e0113fe?xsec_token=ABI3em6IiaUIRqExaIZVCbAtGilBYhM6gGElUOHERoSfc=",
  "note_id": "6958f9db000000001e0113fe",
  "title": "你为什么总是卖飞在黎明前的黑暗？",
  "author": "Mr.西土瓦",
  "content": "你卖飞的地方，大概率是在某种支撑位附近，比如趋势线、移动平均线，前高或前低，多头入场K线的低点（潜在支撑位），多头信号K线的高点（潜在支撑位），任何类型的交易区间，大阳线的高点或低点（潜在支撑位）。行情在即将抵达这些价位时，往往会急速下挫，让你错误的以为，行情将要持续且猛烈的下跌，从而把你洗出场外。当行情抵达支撑位后，往往又迅速反转，且势头强劲。\n\t\n价格行为深度解析如下：\n强势多头预期行情将抵达支撑位，想要以更低的价格买入，所以在抵达支撑位之前，他们停止买入，等待行情抵达支撑位后再买入。\n\t\n强势空头也预期行情将抵达支撑位，想要以更低的价格止盈，所以在抵达支撑位之前，他们疯狂卖出，等待行情抵达支撑位后再止盈。\n\t\n强势多头的停止买入和强势空头的疯狂卖出，导致多空双方力量严重失衡，空方占据绝对优势，造就了抵达支撑位时的急速下挫。\n\t\n当行情抵达支撑位，前期等待的强势多头疯狂买入，前期等待的强势空头迅速止盈，并反手做多。此时，多空双方力量再度严重失衡，多方占据绝对优势，造就了行情迅速反转，且势头强劲。#阿布价格行为 #价格行为学 #价格行为分析 #阿布价格行为学 #价格行为交易 #炒股日记",
  "images": [
    "https://fe-platform.xhscdn.com/platform/104101l0320so64n6nk062u7au7rdm9g007pkcqvqmd668?imageView2/2/format/webp",
    "https://fe-platform.xhscdn.com/platform/104101l0321829dg07k06jn2ge0jp60000000007dp7iga.png?imageView2/2/format/webp",
    "https://fe-platform.xhscdn.com/platform/104101l03210hgobqnu062u7au7rdm9g007pkcqst0kbve?imageView2/2/w/198/format/webp",
    "https://fe-platform.xhscdn.com/platform/104101l03210hgoi2nu062u7au7rdm9g007pkcqtn1j2u4?imageView2/2/w/198/format/webp",
    "https://sns-webpic-qc.xhscdn.com/202606122343/4a5013d07910ab9df958724da17f7f5a/notes_pre_post/1040g3k031qsilvc4mu005pjkddphov6lcutscu8!nd_dft_wlteh_webp_3"
  ],
  "local_images": [
    "D:\\hb\\xhs-scraper\\output\\Mr.西土瓦\\你为什么总是卖飞在黎明前的黑暗？\\images\\img_01.webp",
    "D:\\hb\\xhs-scraper\\output\\Mr.西土瓦\\你为什么总是卖飞在黎明前的黑暗？\\images\\img_02.webp",
    "D:\\hb\\xhs-scraper\\output\\Mr.西土瓦\\你为什么总是卖飞在黎明前的黑暗？\\images\\img_03.webp",
    "D:\\hb\\xhs-scraper\\output\\Mr.西土瓦\\你为什么总是卖飞在黎明前的黑暗？\\images\\img_04.webp",
    "D:\\hb\\xhs-scraper\\output\\Mr.西土瓦\\你为什么总是卖飞在黎明前的黑暗？\\images\\img_05.webp"
  ],
  "likes": 20,
  "collects": 10,
  "comments": [
    {
      "id": "69591c2700000000090364e5",
      "user": "阿斯克勒庇俄斯",
      "content": "最近再重新读阿布的书，第一章，第二章提到了，谢谢",
      "likes": 3,
      "time_str": 1767447592000,
      "replies": [],
      "sub_count": 2
    }
  ],
  "comment_count": 1
}